{
  "status": "ok",
  "cachedAt": "2026-06-29T07:31:45.438Z",
  "value": {
    "batchcomplete": true,
    "query": {
      "geosearch": [
        {
          "pageid": 12566093,
          "ns": 0,
          "title": "Q11427321",
          "lat": 35.742361,
          "lon": 139.825972,
          "dist": 16.6,
          "primary": true
        },
        {
          "pageid": 95647963,
          "ns": 0,
          "title": "Q97207471",
          "lat": 35.74263888888889,
          "lon": 139.82808333333332,
          "dist": 184,
          "primary": true
        },
        {
          "pageid": 104496572,
          "ns": 0,
          "title": "Q109328756",
          "lat": 35.74368,
          "lon": 139.82883,
          "dist": 293,
          "primary": true
        },
        {
          "pageid": 12202771,
          "ns": 0,
          "title": "Q10930485",
          "lat": 35.744166666667,
          "lon": 139.82355555556,
          "dist": 313,
          "primary": true
        },
        {
          "pageid": 18821274,
          "ns": 0,
          "title": "Q17224477",
          "lat": 35.744278,
          "lon": 139.828556,
          "dist": 315.9,
          "primary": true
        },
        {
          "pageid": 104496707,
          "ns": 0,
          "title": "Q109328988",
          "lat": 35.7461,
          "lon": 139.82651,
          "dist": 429.3,
          "primary": true
        },
        {
          "pageid": 104496830,
          "ns": 0,
          "title": "Q109329133",
          "lat": 35.74627,
          "lon": 139.82648,
          "dist": 447.9,
          "primary": true
        },
        {
          "pageid": 81275560,
          "ns": 0,
          "title": "Q81917435",
          "lat": 35.739803,
          "lon": 139.830551,
          "dist": 485.4,
          "primary": true
        },
        {
          "pageid": 7746048,
          "ns": 0,
          "title": "Q7813847",
          "lat": 35.7379,
          "lon": 139.827,
          "dist": 490.9,
          "primary": true
        },
        {
          "pageid": 102117930,
          "ns": 0,
          "title": "Q106852601",
          "lat": 35.747172,
          "lon": 139.82888,
          "dist": 601.7,
          "primary": true
        },
        {
          "pageid": 104496814,
          "ns": 0,
          "title": "Q109329118",
          "lat": 35.7472,
          "lon": 139.82886,
          "dist": 603.7,
          "primary": true
        },
        {
          "pageid": 81322252,
          "ns": 0,
          "title": "Q81964278",
          "lat": 35.741234,
          "lon": 139.832748,
          "dist": 610.6,
          "primary": true
        },
        {
          "pageid": 5673691,
          "ns": 0,
          "title": "Q5903250",
          "lat": 35.747638888888886,
          "lon": 139.8275,
          "dist": 612,
          "primary": true
        },
        {
          "pageid": 12566082,
          "ns": 0,
          "title": "Q11427310",
          "lat": 35.747675,
          "lon": 139.82769444444443,
          "dist": 619.7,
          "primary": true
        },
        {
          "pageid": 31055141,
          "ns": 0,
          "title": "Q29408059",
          "lat": 35.74611111,
          "lon": 139.83138889,
          "dist": 641.7,
          "primary": true
        },
        {
          "pageid": 104772083,
          "ns": 0,
          "title": "Q109658463",
          "lat": 35.74019,
          "lon": 139.83368,
          "dist": 721.6,
          "primary": true
        },
        {
          "pageid": 101898587,
          "ns": 0,
          "title": "Q106617363",
          "lat": 35.736805555555556,
          "lon": 139.8305,
          "dist": 724.4,
          "primary": true
        },
        {
          "pageid": 113537738,
          "ns": 0,
          "title": "Q119033311",
          "lat": 35.73816,
          "lon": 139.81977,
          "dist": 730.5,
          "primary": true
        },
        {
          "pageid": 101730848,
          "ns": 0,
          "title": "Q106434972",
          "lat": 35.73988888888889,
          "lon": 139.83369444444443,
          "dist": 734.1,
          "primary": true
        },
        {
          "pageid": 102117745,
          "ns": 0,
          "title": "Q106852448",
          "lat": 35.748043,
          "lon": 139.82216,
          "dist": 735.4,
          "primary": true
        }
      ]
    }
  }
}
