{
  "status": "ok",
  "cachedAt": "2026-06-29T07:34:43.413Z",
  "value": {
    "batchcomplete": true,
    "query": {
      "geosearch": [
        {
          "pageid": 112971007,
          "ns": 0,
          "title": "Q118464840",
          "lat": 35.67096,
          "lon": 139.86628,
          "dist": 131.8,
          "primary": true
        },
        {
          "pageid": 102117768,
          "ns": 0,
          "title": "Q106852470",
          "lat": 35.67030555555556,
          "lon": 139.86552777777777,
          "dist": 132.9,
          "primary": true
        },
        {
          "pageid": 102103201,
          "ns": 0,
          "title": "Q106836965",
          "lat": 35.67058333333333,
          "lon": 139.86694444444444,
          "dist": 203.7,
          "primary": true
        },
        {
          "pageid": 95633342,
          "ns": 0,
          "title": "Q97192716",
          "lat": 35.67333333333333,
          "lon": 139.86294444444445,
          "dist": 280,
          "primary": true
        },
        {
          "pageid": 544772,
          "ns": 0,
          "title": "Q579185",
          "lat": 35.669806,
          "lon": 139.86775,
          "dist": 310.6,
          "primary": true
        },
        {
          "pageid": 81275728,
          "ns": 0,
          "title": "Q81917602",
          "lat": 35.67432,
          "lon": 139.865219,
          "dist": 326.4,
          "primary": true
        },
        {
          "pageid": 81275704,
          "ns": 0,
          "title": "Q81917579",
          "lat": 35.667599,
          "lon": 139.864914,
          "dist": 422.1,
          "primary": true
        },
        {
          "pageid": 12690953,
          "ns": 0,
          "title": "Q11551034",
          "lat": 35.668,
          "lon": 139.862556,
          "dist": 433.8,
          "primary": true
        },
        {
          "pageid": 81275639,
          "ns": 0,
          "title": "Q81917514",
          "lat": 35.669933,
          "lon": 139.860275,
          "dist": 450.2,
          "primary": true
        },
        {
          "pageid": 12783983,
          "ns": 0,
          "title": "Q11643513",
          "lat": 35.667861,
          "lon": 139.867833,
          "dist": 472.8,
          "primary": true
        },
        {
          "pageid": 12588655,
          "ns": 0,
          "title": "Q11449188",
          "lat": 35.67359,
          "lon": 139.85949,
          "dist": 548.1,
          "primary": true
        },
        {
          "pageid": 12542614,
          "ns": 0,
          "title": "Q11403976",
          "lat": 35.67313055555555,
          "lon": 139.85909444444445,
          "dist": 560.7,
          "primary": true
        },
        {
          "pageid": 12690982,
          "ns": 0,
          "title": "Q11551063",
          "lat": 35.671,
          "lon": 139.8584,
          "dist": 590.8,
          "primary": true
        },
        {
          "pageid": 12588656,
          "ns": 0,
          "title": "Q11449189",
          "lat": 35.67698055555555,
          "lon": 139.86276388888888,
          "dist": 651,
          "primary": true
        },
        {
          "pageid": 12690979,
          "ns": 0,
          "title": "Q11551060",
          "lat": 35.665356,
          "lon": 139.863281,
          "dist": 687.7,
          "primary": true
        },
        {
          "pageid": 12664938,
          "ns": 0,
          "title": "Q11525064",
          "lat": 35.664929,
          "lon": 139.864283,
          "dist": 721.3,
          "primary": true
        },
        {
          "pageid": 12761404,
          "ns": 0,
          "title": "Q11620997",
          "lat": 35.665926,
          "lon": 139.869581,
          "dist": 739.5,
          "primary": true
        },
        {
          "pageid": 12505051,
          "ns": 0,
          "title": "Q11366978",
          "lat": 35.66576944444444,
          "lon": 139.8695888888889,
          "dist": 754.3,
          "primary": true
        },
        {
          "pageid": 81322286,
          "ns": 0,
          "title": "Q81964313",
          "lat": 35.671516,
          "lon": 139.873306,
          "dist": 757.4,
          "primary": true
        },
        {
          "pageid": 81275634,
          "ns": 0,
          "title": "Q81917508",
          "lat": 35.671516,
          "lon": 139.873306,
          "dist": 757.4,
          "primary": true
        }
      ]
    }
  }
}
