{
  "status": "ok",
  "cachedAt": "2026-06-29T07:27:42.647Z",
  "value": {
    "batchcomplete": true,
    "query": {
      "geosearch": [
        {
          "pageid": 94613012,
          "ns": 0,
          "title": "Q95744478",
          "lat": 35.74766666666667,
          "lon": 139.79991666666666,
          "dist": 147.1,
          "primary": true
        },
        {
          "pageid": 95643486,
          "ns": 0,
          "title": "Q97202885",
          "lat": 35.74711111111111,
          "lon": 139.7993888888889,
          "dist": 166.4,
          "primary": true
        },
        {
          "pageid": 30352359,
          "ns": 0,
          "title": "Q28692763",
          "lat": 35.74533611111111,
          "lon": 139.80063055555556,
          "dist": 177.1,
          "primary": true
        },
        {
          "pageid": 12459820,
          "ns": 0,
          "title": "Q11321378",
          "lat": 35.748417,
          "lon": 139.802194,
          "dist": 194.9,
          "primary": true
        },
        {
          "pageid": 12544003,
          "ns": 0,
          "title": "Q11405355",
          "lat": 35.747,
          "lon": 139.803417,
          "dist": 200.1,
          "primary": true
        },
        {
          "pageid": 105027565,
          "ns": 0,
          "title": "Q109929637",
          "lat": 35.74614,
          "lon": 139.80333,
          "dist": 207.6,
          "primary": true
        },
        {
          "pageid": 95642644,
          "ns": 0,
          "title": "Q97202023",
          "lat": 35.74952777777778,
          "lon": 139.8010277777778,
          "dist": 297.3,
          "primary": true
        },
        {
          "pageid": 12705606,
          "ns": 0,
          "title": "Q11565670",
          "lat": 35.749556,
          "lon": 139.800611,
          "dist": 304.8,
          "primary": true
        },
        {
          "pageid": 102102876,
          "ns": 0,
          "title": "Q106836640",
          "lat": 35.747194444444446,
          "lon": 139.79783333333333,
          "dist": 306.7,
          "primary": true
        },
        {
          "pageid": 105027402,
          "ns": 0,
          "title": "Q109929443",
          "lat": 35.74418,
          "lon": 139.80206,
          "dist": 307.6,
          "primary": true
        },
        {
          "pageid": 95645216,
          "ns": 0,
          "title": "Q97204655",
          "lat": 35.74883333333333,
          "lon": 139.80377777777778,
          "dist": 319.5,
          "primary": true
        },
        {
          "pageid": 95644001,
          "ns": 0,
          "title": "Q97203419",
          "lat": 35.74402777777778,
          "lon": 139.80211111111112,
          "dist": 325.1,
          "primary": true
        },
        {
          "pageid": 105025229,
          "ns": 0,
          "title": "Q109927617",
          "lat": 35.7456,
          "lon": 139.79784,
          "dist": 334.5,
          "primary": true
        },
        {
          "pageid": 56588006,
          "ns": 0,
          "title": "Q56648122",
          "lat": 35.749194,
          "lon": 139.798778,
          "dist": 339.8,
          "primary": true
        },
        {
          "pageid": 95644220,
          "ns": 0,
          "title": "Q97203640",
          "lat": 35.74413888888889,
          "lon": 139.79922222222223,
          "dist": 351.4,
          "primary": true
        },
        {
          "pageid": 12501087,
          "ns": 0,
          "title": "Q11363084",
          "lat": 35.74597222,
          "lon": 139.805,
          "dist": 356.2,
          "primary": true
        },
        {
          "pageid": 30352355,
          "ns": 0,
          "title": "Q28692759",
          "lat": 35.74915,
          "lon": 139.79787777777779,
          "dist": 393.9,
          "primary": true
        },
        {
          "pageid": 113538158,
          "ns": 0,
          "title": "Q119033729",
          "lat": 35.74668,
          "lon": 139.80567,
          "dist": 403.3,
          "primary": true
        },
        {
          "pageid": 12544001,
          "ns": 0,
          "title": "Q11405353",
          "lat": 35.74727,
          "lon": 139.79668,
          "dist": 411.1,
          "primary": true
        },
        {
          "pageid": 64923636,
          "ns": 0,
          "title": "Q65283523",
          "lat": 35.745777777778,
          "lon": 139.79658333333,
          "dist": 434.2,
          "primary": true
        }
      ]
    }
  }
}
