{
  "status": "ok",
  "cachedAt": "2026-06-29T07:13:00.664Z",
  "value": {
    "batchcomplete": true,
    "query": {
      "geosearch": [
        {
          "pageid": 12429138,
          "ns": 0,
          "title": "Q11288418",
          "lat": 35.673833,
          "lon": 139.767306,
          "dist": 63.6,
          "primary": true
        },
        {
          "pageid": 12481980,
          "ns": 0,
          "title": "Q11344050",
          "lat": 35.67268,
          "lon": 139.76837,
          "dist": 98.7,
          "primary": true
        },
        {
          "pageid": 106375392,
          "ns": 0,
          "title": "Q111406709",
          "lat": 35.67345,
          "lon": 139.76917,
          "dist": 120.7,
          "primary": true
        },
        {
          "pageid": 317428,
          "ns": 0,
          "title": "Q331185",
          "lat": 35.674346,
          "lon": 139.767047,
          "dist": 122,
          "primary": true
        },
        {
          "pageid": 106375395,
          "ns": 0,
          "title": "Q111406712",
          "lat": 35.67288,
          "lon": 139.76903,
          "dist": 125.5,
          "primary": true
        },
        {
          "pageid": 122664194,
          "ns": 0,
          "title": "Q128687191",
          "lat": 35.67347222222222,
          "lon": 139.76644444444443,
          "dist": 125.5,
          "primary": true
        },
        {
          "pageid": 12429135,
          "ns": 0,
          "title": "Q11288415",
          "lat": 35.672194,
          "lon": 139.768333,
          "dist": 147.2,
          "primary": true
        },
        {
          "pageid": 6240385,
          "ns": 0,
          "title": "Q6424456",
          "lat": 35.671974,
          "lon": 139.767397,
          "dist": 169.2,
          "primary": true
        },
        {
          "pageid": 106375391,
          "ns": 0,
          "title": "Q111406708",
          "lat": 35.67407,
          "lon": 139.76955,
          "dist": 169.5,
          "primary": true
        },
        {
          "pageid": 118975788,
          "ns": 0,
          "title": "Q124788953",
          "lat": 35.671967,
          "lon": 139.767249,
          "dist": 173.6,
          "primary": true
        },
        {
          "pageid": 119525872,
          "ns": 0,
          "title": "Q125398479",
          "lat": 35.6737,
          "lon": 139.7659,
          "dist": 176.8,
          "primary": true
        },
        {
          "pageid": 125453126,
          "ns": 0,
          "title": "Q131541975",
          "lat": 35.67344444444444,
          "lon": 139.76580555555554,
          "dist": 183.2,
          "primary": true
        },
        {
          "pageid": 12707633,
          "ns": 0,
          "title": "Q11567697",
          "lat": 35.672711,
          "lon": 139.766017,
          "dist": 183.8,
          "primary": true
        },
        {
          "pageid": 51036026,
          "ns": 0,
          "title": "Q50036782",
          "lat": 35.673196,
          "lon": 139.769844,
          "dist": 183.8,
          "primary": true
        },
        {
          "pageid": 106783126,
          "ns": 0,
          "title": "Q111866128",
          "lat": 35.6722,
          "lon": 139.76927,
          "dist": 190.4,
          "primary": true
        },
        {
          "pageid": 12486723,
          "ns": 0,
          "title": "Q11348834",
          "lat": 35.67463889,
          "lon": 139.76947222,
          "dist": 198.1,
          "primary": true
        },
        {
          "pageid": 1565428,
          "ns": 0,
          "title": "Q1631032",
          "lat": 35.67476111,
          "lon": 139.76936667,
          "dist": 200.7,
          "primary": true
        },
        {
          "pageid": 99231930,
          "ns": 0,
          "title": "Q102669637",
          "lat": 35.6753,
          "lon": 139.768839,
          "dist": 224.4,
          "primary": true
        },
        {
          "pageid": 18820652,
          "ns": 0,
          "title": "Q17223949",
          "lat": 35.672083,
          "lon": 139.769722,
          "dist": 228.7,
          "primary": true
        },
        {
          "pageid": 107228218,
          "ns": 0,
          "title": "Q112334821",
          "lat": 35.67144444444445,
          "lon": 139.76716666666667,
          "dist": 231.4,
          "primary": true
        }
      ]
    }
  }
}
