{
  "status": "ok",
  "cachedAt": "2026-06-29T06:05:58.453Z",
  "value": {
    "batchcomplete": true,
    "query": {
      "geosearch": [
        {
          "pageid": 12326272,
          "ns": 0,
          "title": "Q11132560",
          "lat": 35.67637777777778,
          "lon": 139.6422388888889,
          "dist": 72.6,
          "primary": true
        },
        {
          "pageid": 104050846,
          "ns": 0,
          "title": "Q108814628",
          "lat": 35.67616,
          "lon": 139.64285,
          "dist": 94,
          "primary": true
        },
        {
          "pageid": 12512802,
          "ns": 0,
          "title": "Q11374606",
          "lat": 35.676639,
          "lon": 139.64225,
          "dist": 100.3,
          "primary": true
        },
        {
          "pageid": 131773,
          "ns": 0,
          "title": "Q129814",
          "lat": 35.676847,
          "lon": 139.641938,
          "dist": 118.9,
          "primary": true
        },
        {
          "pageid": 4192782,
          "ns": 0,
          "title": "Q4389461",
          "lat": 35.67597222222222,
          "lon": 139.64358333333334,
          "dist": 151.6,
          "primary": true
        },
        {
          "pageid": 81275103,
          "ns": 0,
          "title": "Q81916972",
          "lat": 35.673054,
          "lon": 139.63942,
          "dist": 377.9,
          "primary": true
        },
        {
          "pageid": 12690236,
          "ns": 0,
          "title": "Q11550316",
          "lat": 35.672444,
          "lon": 139.64325,
          "dist": 389.6,
          "primary": true
        },
        {
          "pageid": 95640708,
          "ns": 0,
          "title": "Q97200087",
          "lat": 35.6725,
          "lon": 139.64388888888888,
          "dist": 405.4,
          "primary": true
        },
        {
          "pageid": 95641458,
          "ns": 0,
          "title": "Q97200838",
          "lat": 35.67575,
          "lon": 139.64725,
          "dist": 481.3,
          "primary": true
        },
        {
          "pageid": 7601984,
          "ns": 0,
          "title": "Q7676991",
          "lat": 35.6804,
          "lon": 139.643,
          "dist": 523.1,
          "primary": true
        },
        {
          "pageid": 12556558,
          "ns": 0,
          "title": "Q11417824",
          "lat": 35.676423,
          "lon": 139.647758,
          "dist": 532,
          "primary": true
        },
        {
          "pageid": 7746197,
          "ns": 0,
          "title": "Q7813983",
          "lat": 35.6699,
          "lon": 139.641,
          "dist": 658.8,
          "primary": true
        },
        {
          "pageid": 103393089,
          "ns": 0,
          "title": "Q108123262",
          "lat": 35.678257816306605,
          "lon": 139.63514158511083,
          "dist": 671.7,
          "primary": true
        },
        {
          "pageid": 34532,
          "ns": 0,
          "title": "Q31589",
          "lat": 35.678777777777775,
          "lon": 139.63538888888888,
          "dist": 677.9,
          "primary": true
        },
        {
          "pageid": 95640877,
          "ns": 0,
          "title": "Q97200257",
          "lat": 35.67936111111111,
          "lon": 139.63575,
          "dist": 685.3,
          "primary": true
        },
        {
          "pageid": 81322093,
          "ns": 0,
          "title": "Q81964120",
          "lat": 35.674553,
          "lon": 139.649506,
          "dist": 698.4,
          "primary": true
        },
        {
          "pageid": 114192074,
          "ns": 0,
          "title": "Q119710716",
          "lat": 35.674553,
          "lon": 139.649506,
          "dist": 698.4,
          "primary": true
        },
        {
          "pageid": 81275106,
          "ns": 0,
          "title": "Q81916975",
          "lat": 35.674553,
          "lon": 139.649506,
          "dist": 698.4,
          "primary": true
        },
        {
          "pageid": 126221334,
          "ns": 0,
          "title": "Q132349193",
          "lat": 35.673639,
          "lon": 139.634023,
          "dist": 752.1,
          "primary": true
        },
        {
          "pageid": 81322086,
          "ns": 0,
          "title": "Q81964113",
          "lat": 35.672333,
          "lon": 139.63472,
          "dist": 754.9,
          "primary": true
        }
      ]
    }
  }
}
