{
  "status": "ok",
  "cachedAt": "2026-06-29T07:03:45.427Z",
  "value": {
    "batchcomplete": true,
    "query": {
      "geosearch": [
        {
          "pageid": 85146734,
          "ns": 0,
          "title": "Q85876174",
          "lat": 35.69841666666667,
          "lon": 139.70388888888888,
          "dist": 11.6,
          "primary": true
        },
        {
          "pageid": 106116411,
          "ns": 0,
          "title": "Q111121686",
          "lat": 35.6990062,
          "lon": 139.7038187,
          "dist": 63.3,
          "primary": true
        },
        {
          "pageid": 12402598,
          "ns": 0,
          "title": "Q11257440",
          "lat": 35.697917,
          "lon": 139.702972,
          "dist": 92,
          "primary": true
        },
        {
          "pageid": 12737027,
          "ns": 0,
          "title": "Q11596884",
          "lat": 35.69789,
          "lon": 139.7053,
          "dist": 151.6,
          "primary": true
        },
        {
          "pageid": 106782987,
          "ns": 0,
          "title": "Q111865989",
          "lat": 35.6975,
          "lon": 139.70247,
          "dist": 156.6,
          "primary": true
        },
        {
          "pageid": 1199017,
          "ns": 0,
          "title": "Q1258165",
          "lat": 35.69694444,
          "lon": 139.70444444,
          "dist": 177.2,
          "primary": true
        },
        {
          "pageid": 106920218,
          "ns": 0,
          "title": "Q112008832",
          "lat": 35.697098,
          "lon": 139.70267,
          "dist": 178.8,
          "primary": true
        },
        {
          "pageid": 26823678,
          "ns": 0,
          "title": "Q24862867",
          "lat": 35.69843611,
          "lon": 139.70575556,
          "dist": 179.9,
          "primary": true
        },
        {
          "pageid": 106920217,
          "ns": 0,
          "title": "Q112008831",
          "lat": 35.697533,
          "lon": 139.7019,
          "dist": 196.1,
          "primary": true
        },
        {
          "pageid": 18812988,
          "ns": 0,
          "title": "Q17217583",
          "lat": 35.69875,
          "lon": 139.70155556,
          "dist": 202.3,
          "primary": true
        },
        {
          "pageid": 6268872,
          "ns": 0,
          "title": "Q6452031",
          "lat": 35.697147811328925,
          "lon": 139.70540018333287,
          "dist": 206,
          "primary": true
        },
        {
          "pageid": 12570815,
          "ns": 0,
          "title": "Q11432041",
          "lat": 35.69972222222222,
          "lon": 139.70555555555555,
          "dist": 215.8,
          "primary": true
        },
        {
          "pageid": 81274537,
          "ns": 0,
          "title": "Q81916411",
          "lat": 35.698948,
          "lon": 139.706146,
          "dist": 222.5,
          "primary": true
        },
        {
          "pageid": 106116388,
          "ns": 0,
          "title": "Q111121663",
          "lat": 35.6993629,
          "lon": 139.7013084,
          "dist": 244.3,
          "primary": true
        },
        {
          "pageid": 120479886,
          "ns": 0,
          "title": "Q126454791",
          "lat": 35.69743,
          "lon": 139.7013341,
          "dist": 246.4,
          "primary": true
        },
        {
          "pageid": 12665123,
          "ns": 0,
          "title": "Q11525249",
          "lat": 35.696944,
          "lon": 139.701667,
          "dist": 251.9,
          "primary": true
        },
        {
          "pageid": 12665132,
          "ns": 0,
          "title": "Q11525258",
          "lat": 35.6966663,
          "lon": 139.7013143,
          "dist": 296.2,
          "primary": true
        },
        {
          "pageid": 111680371,
          "ns": 0,
          "title": "Q116917907",
          "lat": 35.6954844,
          "lon": 139.7035426,
          "dist": 329.1,
          "primary": true
        },
        {
          "pageid": 106236148,
          "ns": 0,
          "title": "Q111253878",
          "lat": 35.69552777777778,
          "lon": 139.70258333333334,
          "dist": 340.8,
          "primary": true
        },
        {
          "pageid": 12641555,
          "ns": 0,
          "title": "Q11501871",
          "lat": 35.696667,
          "lon": 139.706944,
          "dist": 348.3,
          "primary": true
        }
      ]
    }
  }
}
